aio_stdout/__init__.py
aio_stdout/_aio_stdout.py
aio_stdout-0.0.5.dist-info/LICENSE
aio_stdout-0.0.5.dist-info/METADATA
aio_stdout-0.0.5.dist-info/WHEEL
aio_stdout-0.0.5.dist-info/top_level.txt
aio_stdout-0.0.5.dist-info/RECORD
