Metadata-Version: 2.1
Name: aio-stdout
Version: 0.0.5
Summary: The purpose of this package is to provide asynchronous variants of the builtin `input` and `print` functions.
Home-page: https://github.com/SimpleArt/aio-stdout
Author: Jack Nguyen
Author-email: jackyeenguyen@gmail.com
Classifier: Programming Language :: Python :: 3
Classifier: License :: OSI Approved :: MIT License
Classifier: Operating System :: OS Independent
Requires-Python: >=3.7
License-File: LICENSE
